json_leaves
