Metadata-Version: 2.1
Name: json-leaves
Version: 1.2.0
Summary: Extract the leaves from a JSON file and show the paths to said leaves
Home-page: https://github.com/talwrii/json-leaves
Author: @readwithai
Author-email: talwrii@gmail.com
License: MIT
Keywords: JSON,leaves,cli
